MATLAB2PYTHONLIB/__init__.py
MATLAB2PYTHONLIB/functions.py
MATLAB2PYTHONLIB/utils.py
matlab2pythonlib-0.2.8.dist-info/licenses/LICENSE
matlab2pythonlib-0.2.8.dist-info/METADATA
matlab2pythonlib-0.2.8.dist-info/WHEEL
matlab2pythonlib-0.2.8.dist-info/top_level.txt
matlab2pythonlib-0.2.8.dist-info/RECORD
