Metadata-Version: 2.4
Name: matlab2pythonlib
Version: 0.2.8
Summary: Esta librería contiene funciones que permiten la conversión de fechas de formato MATLAB (datenum) al formato datetime de python. También contiene funciones para crear array de tiempo o convertir fácilmente fechas de formato datetime a datestr
Home-page: https://github.com/Fernandojbf123/MATLAB2PYTHONLIB
Author: BelloDev
Author-email: BelloDev <fernandojbf123@gmail.com>
License: MIT
License-File: LICENSE
Dynamic: author
Dynamic: home-page
Dynamic: license-file
